modelscope_image_mcp/__init__.py
modelscope_image_mcp/server.py
modelscope_image_mcp-1.1.0.dist-info/METADATA
modelscope_image_mcp-1.1.0.dist-info/WHEEL
modelscope_image_mcp-1.1.0.dist-info/entry_points.txt
modelscope_image_mcp-1.1.0.dist-info/licenses/LICENSE
modelscope_image_mcp-1.1.0.dist-info/RECORD
