Metadata-Version: 2.4
Name: modelscope-image-mcp
Version: 1.1.0
Summary: MCP Server for ModelScope Qwen-Image text-to-image generation
Project-URL: Homepage, https://github.com/zym9863/modelscope-image-mcp
Project-URL: Repository, https://github.com/zym9863/modelscope-image-mcp
Project-URL: Bug Tracker, https://github.com/zym9863/modelscope-image-mcp/issues
Author-email: zym9863 <ym214413520@gmail.com>
License: MIT License
License-File: LICENSE
Keywords: ai,generation,image,mcp,modelscope,qwen
Classifier: Development Status :: 4 - Beta
Classifier: Intended Audience :: Developers
Classifier: License :: OSI Approved :: MIT License
Classifier: Programming Language :: Python :: 3
Classifier: Programming Language :: Python :: 3.10
Classifier: Programming Language :: Python :: 3.11
Classifier: Programming Language :: Python :: 3.12
Classifier: Topic :: Scientific/Engineering :: Artificial Intelligence
Classifier: Topic :: Software Development :: Libraries :: Python Modules
Requires-Python: >=3.10
Requires-Dist: httpx>=0.27.0
Requires-Dist: mcp>=1.0.0
Requires-Dist: pillow
Requires-Dist: python-dotenv
Requires-Dist: requests
